Metadata-Version: 2.1
Name: image-proccessing
Version: 0.0.1
Summary: Image Proccessing Package using Skimage
Home-page: https://github.com/Guedes96/Image_Processing
Author: Arthur guedes
Author-email: arthurguedesr96@gmail.com
License: UNKNOWN
Platform: UNKNOWN
Requires-Python: >=3.8
Requires-Dist: matplotlib
Requires-Dist: numpy
Requires-Dist: scikit-image (>=0.16.1)
